README.rst
setup.py
django_last_modified.egg-info/PKG-INFO
django_last_modified.egg-info/SOURCES.txt
django_last_modified.egg-info/dependency_links.txt
django_last_modified.egg-info/top_level.txt
last_modified/__init__.py
last_modified/cache_control.py
last_modified/last_modified.py
last_modified/middleware.py
last_modified/models.py
last_modified/tests.py