Metadata-Version: 1.1
Name: django-last-modified
Version: 0.1
Summary: Django middleware for adding freshness and validation cache headers
Home-page: http://github.com/edavis/django-last-modified
Author: Eric Davis
Author-email: ed@npri.org
License: MIT
Keywords: cache,if-modified-since,last-modified,cache-control,expires,etag,if-none-match
Platform: UNKNOWN
Classifier: Development Status :: 4 - Beta
Classifier: Framework :: Django
Classifier: Intended Audience :: Developers
Classifier: License :: OSI Approved :: MIT License
Classifier: Topic :: Internet
